vercel_ai_sdk/__init__.py
vercel_ai_sdk/ai_sdk_ui/__init__.py
vercel_ai_sdk/ai_sdk_ui/adapter.py
vercel_ai_sdk/anthropic/__init__.py
vercel_ai_sdk/core/__init__.py
vercel_ai_sdk/core/messages.py
vercel_ai_sdk/core/runtime.py
vercel_ai_sdk/core/tools.py
vercel_ai_sdk/mcp/__init__.py
vercel_ai_sdk/mcp/client.py
vercel_ai_sdk/openai/__init__.py
vercel_ai_sdk/py.typed
vercel_ai_sdk-0.0.1.dev1.dist-info/WHEEL
vercel_ai_sdk-0.0.1.dev1.dist-info/METADATA
vercel_ai_sdk-0.0.1.dev1.dist-info/RECORD
