Metadata-Version: 2.3
Name: vercel-ai-sdk
Version: 0.0.1.dev1
Summary: The AI Toolkit for Python
Author: Andrey Buzin
Author-email: Andrey Buzin <andrey.buzin@vercel.com>
Requires-Dist: anthropic>=0.40.0
Requires-Dist: httpx>=0.28.1
Requires-Dist: mcp>=1.18.0
Requires-Dist: openai>=2.14.0
Requires-Dist: pydantic>=2.12.5
Requires-Python: >=3.12
